rag_kmk/__init__.py
rag_kmk/logging_setup.py
rag_kmk/rag_client.py
rag_kmk/chat_flow/__init__.py
rag_kmk/chat_flow/llm_interface.py
rag_kmk/config/__init__.py
rag_kmk/config/config.py
rag_kmk/config/config.yaml
rag_kmk/knowledge_base/__init__.py
rag_kmk/knowledge_base/document_loader.py
rag_kmk/knowledge_base/text_splitter.py
rag_kmk/vector_db/__init__.py
rag_kmk/vector_db/database.py
rag_kmk/vector_db/query.py
rag_kmk-0.0.55.dist-info/licenses/LICENSE
rag_kmk-0.0.55.dist-info/METADATA
rag_kmk-0.0.55.dist-info/WHEEL
rag_kmk-0.0.55.dist-info/entry_points.txt
rag_kmk-0.0.55.dist-info/top_level.txt
rag_kmk-0.0.55.dist-info/RECORD
