Metadata-Version: 2.4
Name: rag-kmk
Version: 0.0.55
Summary: A simple RAG implementation for educational purposes implemented by Murat Karakaya Akademi
Author-email: Murat Karakaya <kmkarakaya@gmail.com>
License: MIT License
Project-URL: Homepage, https://github.com/kmkarakaya/rag-kmk
Keywords: rag-kmk
Classifier: Intended Audience :: Developers
Classifier: License :: OSI Approved :: MIT License
Classifier: Natural Language :: English
Classifier: Programming Language :: Python :: 3.8
Classifier: Programming Language :: Python :: 3.9
Classifier: Programming Language :: Python :: 3.10
Classifier: Programming Language :: Python :: 3.11
Classifier: Programming Language :: Python :: 3.12
Requires-Python: >=3.8
License-File: LICENSE
Requires-Dist: numpy==1.26.4
Requires-Dist: PyYAML==6.0.1
Requires-Dist: PyMuPDF==1.26.5
Requires-Dist: python-docx==1.1.2
Requires-Dist: langchain==0.2.10
Requires-Dist: sentence-transformers==3.0.1
Requires-Dist: google-genai==1.43.0
Requires-Dist: chromadb==1.1.1
Requires-Dist: streamlit==1.50.0
Requires-Dist: docx2txt==0.9
Requires-Dist: protobuf==6.32.1
Requires-Dist: packaging==24.2
Requires-Dist: onnxruntime==1.20.1
Provides-Extra: all
Requires-Dist: rag-kmk[extra]; extra == "all"
Provides-Extra: extra
Requires-Dist: pandas; extra == "extra"
Dynamic: license-file
